led_list/__init__.py
led_list/list.py
led_list-0.5.3.dist-info/METADATA
led_list-0.5.3.dist-info/WHEEL
led_list-0.5.3.dist-info/licenses/LICENSE
led_list-0.5.3.dist-info/RECORD
