Metadata-Version: 2.1
Name: led-list
Version: 0.5.3
Summary: Teach Python lists with a BlinkStick LED strip.
Project-URL: Homepage, https://github.com/connorff/led-list
Author-email: Connor Fogarty <connorflynnfogarty@gmail.com>
License-File: LICENSE
Requires-Python: >=3.7
Requires-Dist: blinkstick>=0.7.0
Requires-Dist: pyusb==1.0.0
Requires-Dist: pywinusb
